{
  "id": "Abi",
  "type": "object",
  "additionalProperties": false,
  "required": [
    "objectTypes",
    "enumTypes",
    "interfaceTypes",
    "importedObjectTypes",
    "importedModuleTypes",
    "importedEnumTypes",
    "importedEnvTypes"
  ],
  "properties": {
    "objectTypes": {
      "type": "array",
      "items": {
        "$ref": "#/definitions/objectDefinition"
      }
    },
    "moduleTypes": {
      "type": "array",
      "items": {
        "$ref": "#/definitions/moduleDefinition"
      }
    },
    "enumType": {
      "type": "array",
      "items": {
        "$ref": "#/definitions/enumDefinition"
      }
    },
    "interfaceTypes": {
      "type": "array",
      "items": {
        "$ref": "#/definitions/interfaceDefinition"
      }
    },
    "importedObjectTypes": {
      "type": "array",
      "items": {
        "$ref": "#/definitions/importedObjectDefinition"
      }
    },
    "importedModuleTypes": {
      "type": "array",
      "items": {
        "$ref": "#/definitions/importedModuleDefinition"
      }
    },
    "importedEnumTypes": {
      "type": "array",
      "items": {
        "$ref": "#/definitions/importedEnumDefinition"
      }
    },
    "importedEnvTypes": {
      "type": "array",
      "items": {
        "$ref": "#/definitions/importedEnvDefinition"
      }
    },
    "envType": {
      "$ref": "#/definitions/envDefinition"
    }
  },
  "definitions": {
    "objectDefinition": {
      "type": "object",
      "required": ["properties", "interfaces"],
      "properties": {
        "allOf": [
          {
            "$ref": "#/definitions/genericDefinition"
          },
          {
            "$ref": "#/definitions/withComment"
          }
        ],
        "properties": {
          "type": "array",
          "items": {
            "$ref": "#/definitions/propertyDefinition"
          }
        },
        "interfaces": {
          "type": "array",
          "items": {
            "$ref": "#/definitions/interfaceDefinition"
          }
        }
      },
      "additionalProperties": false
    },
    "moduleDefinition": {
      "type": "object",
      "required": ["methods", "imports", "interfaces"],
      "properties": {
        "allOf": [
          {
            "$ref": "#/definitions/genericDefinition"
          },
          {
            "$ref": "#/definitions/withComment"
          }
        ],
        "methods": {
          "type": "array",
          "items": [
            {
              "$ref": "#/definitions/methodDefinition"
            }
          ]
        },
        "imports": {
          "type": "array",
          "items": [
            {
              "type": "string"
            }
          ]
        },
        "interfaces": {
          "type": "array",
          "items": [
            {
              "$ref": "#/definitions/interfaceImplementedDefinition"
            }
          ]
        }
      },
      "additionalProperties": false
    },
    "interfaceImplementedDefinition": {
      "$ref": "#/definitions/genericDefinition"
    },
    "methodDefinition": {
      "type": "object",
      "required": ["arguments", "return"],
      "properties": {
        "arguments": {
          "type": "array",
          "items": [
            {
              "$ref": "#/definitions/propertyDefinition"
            }
          ]
        },
        "env": {
          "type": "object",
          "properties": {
            "required": {
              "type": "boolean"
            }
          },
          "additionalProperties": false
        },
        "return": {
          "$ref": "#/definitions/propertyDefinition"
        }
      },
      "additionalProperties": false
    },
    "envDefinition": {
      "type": "object",
      "properties": {
        "allOf": [
          {
            "$ref": "#/definitions/objectDefinition"
          }
        ]
      }
    },
    "enumDefinition": {
      "type": "object",
      "required": ["constants"],
      "properties": {
        "allOf": [
          {
            "$ref": "#/definitions/genericDefinition"
          },
          {
            "$ref": "#/definitions/withComment"
          }
        ],
        "constants": {
          "type": "array",
          "items": {
            "type": "string"
          }
        }
      },
      "additionalProperties": false
    },
    "interfaceDefinition": {
      "type": "object",
      "required": ["capabilities"],
      "properties": {
        "allOf": [
          {
            "$ref": "#/definitions/genericDefinition"
          },
          {
            "$ref": "#/definitions/importedDefinition"
          }
        ],
        "capabilities": {
          "$ref": "#/definitions/capabilityDefinition"
        }
      },
      "additionalProperties": false
    },
    "capabilityDefinition": {
      "type": "object",
      "properties": {
        "getImplementations": {
          "type": "object",
          "required": ["enabled"],
          "properties": {
            "enabled": "boolean"
          },
          "additionalProperties": false
        }
      },
      "additionalProperties": false
    },
    "importedDefinition": {
      "type": "object",
      "required": ["uri", "namespace", "nativeType"],
      "properties": {
        "uri": {
          "type": "string"
        },
        "namespace": {
          "type": "string"
        },
        "nativeType": {
          "type": "string"
        }
      },
      "additionalProperties": false
    },
    "importedObjectDefinition": {
      "type": "object",
      "properties": {
        "allOf": [
          {
            "$ref": "#/definitions/objectDefinition"
          },
          {
            "$ref": "#/definitions/importedDefinition"
          },
          {
            "$ref": "#/definitions/withComment"
          }
        ]
      },
      "additionalProperties": false
    },
    "importedModuleDefinition": {
      "type": "object",
      "properties": {
        "allOf": [
          {
            "$ref": "#/definitions/moduleDefinition"
          },
          {
            "$ref": "#/definitions/importedDefinition"
          },
          {
            "$ref": "#/definitions/withComment"
          }
        ]
      },
      "additionalProperties": false
    },
    "importedEnumDefinition": {
      "type": "object",
      "properties": {
        "allOf": [
          {
            "$ref": "#/definitions/enumDefinition"
          },
          {
            "$ref": "#/definitions/importedDefinition"
          },
          {
            "$ref": "#/definitions/withComment"
          }
        ]
      },
      "additionalProperties": false
    },
    "importedEnvDefinition": {
      "type": "object",
      "properties": {
        "allOf": [
          {
            "$ref": "#/definitions/importedObjectDefinition"
          }
        ]
      },
      "additionalProperties": false
    },
    "withKind": {
      "type": "object",
      "properties": {
        "kind": {
          "type": "number"
        }
      },
      "additionalProperties": false,
      "required": ["kind"]
    },
    "withComment": {
      "type": "object",
      "properties": {
        "comment": {
          "type": "string"
        }
      },
      "additionalProperties": false
    },
    "propertyDefinition": {
      "type": "object",
      "allOf": [
        {
          "$ref": "#/definitions/withComment"
        },
        {
          "$ref": "#/definitions/anyDefinition"
        }
      ],
      "additionalProperties": false
    },
    "genericDefinition": {
      "type": "object",
      "properties": {
        "allOf": [
          {
            "$ref": "#/definitions/withKind"
          }
        ],
        "type": {
          "type": "string"
        },
        "name": {
          "type": "string"
        },
        "required": {
          "type": "boolean"
        }
      },
      "additionalProperties": false,
      "required": ["type"]
    },
    "anyDefinition": {
      "type": "object",
      "properties": {
        "allOf": [
          {
            "$ref": "#/definitions/genericDefinition"
          }
        ],
        "array": {
          "$ref": "#/definitions/arrayDefinition"
        },
        "scalar": {
          "$ref": "#/definitions/scalarDefinition"
        },
        "map": {
          "$ref": "#/definitions/mapDefinition"
        },
        "object": {
          "$ref": "#/definitions/objectRef"
        },
        "enum": {
          "$ref": "#/definitions/enumRef"
        },
        "unresolvedObjectOrEnum": {
          "$ref": "#/definitions/unresolvedObjectOrEnumRef"
        }
      },
      "additionalProperties": false
    },
    "arrayDefinition": {
      "type": "object",
      "properties": {
        "allOf": [
          {
            "$ref": "#/definitions/anyDefinition"
          }
        ],
        "item": {
          "$ref": "#/definitions/genericDefinition"
        }
      },
      "additionalProperties": false,
      "required": ["item"]
    },
    "scalarType": {
      "type": "string",
      "enum": [
        "UInt",
        "UInt8",
        "UInt16",
        "UInt32",
        "Int",
        "Int8",
        "Int16",
        "Int32",
        "String",
        "Boolean",
        "Bytes",
        "BigInt",
        "BigNumber",
        "JSON"
      ]
    },
    "scalarDefinition": {
      "type": "object",
      "properties": {
        "type": {
          "$ref": "#/definitions/scalarType"
        }
      },
      "additionalProperties": false,
      "required": ["type"]
    },
    "mapKeyType": {
      "type": "string",
      "enum": [
        "UInt",
        "UInt8",
        "UInt16",
        "UInt32",
        "Int",
        "Int8",
        "Int16",
        "Int32",
        "String"
      ]
    },
    "mapKeyDefinition": {
      "type": "object",
      "properties": {
        "allOf": [
          {
            "$ref": "#/definitions/anyDefinition"
          }
        ],
        "type": {
          "$ref": "#/definitions/mapKeyType"
        }
      },
      "additionalProperties": false,
      "required": ["type"]
    },
    "mapDefinition": {
      "type": "object",
      "properties": {
        "allOf": [
          {
            "$ref": "#/definitions/anyDefinition"
          },
          {
            "$ref": "#/definitions/withComment"
          }
        ],
        "key": {
          "$ref": "#/definitions/mapKeyDefinition"
        },
        "value": {
          "$ref": "#/definitions/genericDefinition"
        }
      },
      "additionalProperties": false,
      "required": ["key", "value"]
    },
    "objectRef": {
      "$ref": "#/definitions/genericDefinition"
    },
    "enumRef": {
      "$ref": "#/definitions/genericDefinition"
    },
    "unresolvedObjectOrEnumRef": {
      "$ref": "#/definitions/genericDefinition"
    }
  }
}
